MANIFEST.in
README.md
__init__.py
requirements.txt
setup.py
mlphys/__init__.py
mlphys.egg-info/PKG-INFO
mlphys.egg-info/SOURCES.txt
mlphys.egg-info/dependency_links.txt
mlphys.egg-info/top_level.txt
mlphys/deepqis/__init__.py
mlphys/deepqis/network/__init__.py
mlphys/deepqis/network/inference.py
mlphys/deepqis/network/models/ARL_ONRL_meas_n_1000_qubits_2_batch_4_alpha_0.1_BEST.h5
mlphys/deepqis/network/models/ARL_ONRL_meas_n_1000_qubits_2_batch_4_alpha_0.4_BEST.h5
mlphys/deepqis/optimization/__init__.py
mlphys/deepqis/optimization/bme.py
mlphys/deepqis/optimization/linear_inversion.py
mlphys/deepqis/optimization/mle.py
mlphys/deepqis/simulator/__init__.py
mlphys/deepqis/simulator/distributions.py
mlphys/deepqis/simulator/measurements.py
mlphys/deepqis/simulator/projectors_array_qs_2_general_scheme.pickle
mlphys/deepqis/utils/Alpha_Measure.py
mlphys/deepqis/utils/Concurrence_Measure.py
mlphys/deepqis/utils/Extract_Net.py
mlphys/deepqis/utils/Fidelity_Measure.py
mlphys/deepqis/utils/Max_Eigen_Measure.py
mlphys/deepqis/utils/Positive_Partial_Trace.py
mlphys/deepqis/utils/Purity_Measure.py
mlphys/deepqis/utils/Rank_Measure.py
mlphys/deepqis/utils/__init__.py
mlphys/deepqis/utils/gen_basis_array.py
mlphys/deepqis/utils/gen_basis_order.py
mlphys/deepqis/utils/projectors_array_qs_2.pickle
mlphys/fso/__init__.py
mlphys/fso/lgoam/__init__.py
mlphys/fso/lgoam/source/OAM_Intensity_Phase.py
mlphys/fso/lgoam/source/__init__.py
mlphys/fso/lgoam/utils/Imaging.py
mlphys/fso/lgoam/utils/Noise.py
mlphys/fso/lgoam/utils/__init__.py
mlphys/fso/turbulence/__init__.py
mlphys/fso/turbulence/gdo_corrected_phase_mask.py
mlphys/fso/turbulence/phase_mask.py
mlphys/fso/turbulence/propagate.py